pypacks/__init__.py
pypacks/core.py
pypacks/function.py
pypacks/types.py
pypacks-1.1.0.dist-info/licenses/LICENSE
pypacks-1.1.0.dist-info/METADATA
pypacks-1.1.0.dist-info/WHEEL
pypacks-1.1.0.dist-info/top_level.txt
pypacks-1.1.0.dist-info/RECORD
