Metadata-Version: 2.4
Name: pypacks
Version: 1.1.0
Summary: A Minecraft pack generator
Author: Block120
Requires-Python: >=3.6
License-File: LICENSE
Dynamic: author
Dynamic: description
Dynamic: description-content-type
Dynamic: license-file
Dynamic: requires-python
Dynamic: summary
